kronecker_attention_pytorch/__init__.py
kronecker_attention_pytorch/kronecker_attention_pytorch.py
kronecker_attention_pytorch-0.0.6.dist-info/LICENSE
kronecker_attention_pytorch-0.0.6.dist-info/METADATA
kronecker_attention_pytorch-0.0.6.dist-info/WHEEL
kronecker_attention_pytorch-0.0.6.dist-info/top_level.txt
kronecker_attention_pytorch-0.0.6.dist-info/RECORD
