Metadata-Version: 2.1
Name: kronecker-attention-pytorch
Version: 0.0.6
Summary: Kronecker Attention - Pytorch
Home-page: https://github.com/lucidrains/kronecker-attention-pytorch
Author: Phil Wang
Author-email: lucidrains@gmail.com
License: MIT
Keywords: artificial intelligence,attention mechanism
Platform: UNKNOWN
Classifier: Development Status :: 4 - Beta
Classifier: Intended Audience :: Developers
Classifier: Topic :: Scientific/Engineering :: Artificial Intelligence
Classifier: License :: OSI Approved :: MIT License
Classifier: Programming Language :: Python :: 3.6
Requires-Dist: torch
Requires-Dist: einops (>=0.3)
